gooey_gui/__init__.py
gooey_gui/components/__init__.py
gooey_gui/components/common.py
gooey_gui/components/input_widgets.py
gooey_gui/components/modal.py
gooey_gui/components/pills.py
gooey_gui/components/url_button.py
gooey_gui/core/__init__.py
gooey_gui/core/exceptions.py
gooey_gui/core/pubsub.py
gooey_gui/core/reloader.py
gooey_gui/core/renderer.py
gooey_gui/core/state.py
gooey_gui/core/state_interactions.py
gooey_gui-0.6.0.dist-info/METADATA
gooey_gui-0.6.0.dist-info/WHEEL
gooey_gui-0.6.0.dist-info/RECORD
